pluggedinkit/__init__.py
pluggedinkit/client.py
pluggedinkit/exceptions.py
pluggedinkit/types.py
pluggedinkit/services/__init__.py
pluggedinkit/services/documents.py
pluggedinkit/services/rag.py
pluggedinkit/services/uploads.py
pluggedinkit-1.0.1.dist-info/licenses/LICENSE
pluggedinkit-1.0.1.dist-info/METADATA
pluggedinkit-1.0.1.dist-info/WHEEL
pluggedinkit-1.0.1.dist-info/top_level.txt
pluggedinkit-1.0.1.dist-info/RECORD
