Metadata-Version: 2.4
Name: pluggedinkit
Version: 1.0.1
Summary: Official Python SDK for Plugged.in Library API
Author-email: "Plugged.in" <sdk@plugged.in>
License: MIT
Project-URL: Homepage, https://github.com/VeriTeknik/pluggedinkit-python
Project-URL: Documentation, https://docs.plugged.in/sdks/python
Project-URL: Repository, https://github.com/VeriTeknik/pluggedinkit-python
Project-URL: Issues, https://github.com/VeriTeknik/pluggedinkit-python/issues
Keywords: pluggedin,api,sdk,library,rag,documents,mcp
Classifier: Development Status :: 5 - Production/Stable
Classifier: Intended Audience :: Developers
Classifier: License :: OSI Approved :: MIT License
Classifier: Programming Language :: Python :: 3
Classifier: Programming Language :: Python :: 3.8
Classifier: Programming Language :: Python :: 3.9
Classifier: Programming Language :: Python :: 3.10
Classifier: Programming Language :: Python :: 3.11
Classifier: Programming Language :: Python :: 3.12
Classifier: Topic :: Software Development :: Libraries :: Python Modules
Classifier: Topic :: Internet :: WWW/HTTP
Classifier: Topic :: Software Development :: Libraries
Requires-Python: >=3.8
License-File: LICENSE
Requires-Dist: httpx>=0.25.0
Requires-Dist: pydantic>=2.0.0
Requires-Dist: typing-extensions>=4.0.0; python_version < "3.11"
Provides-Extra: dev
Requires-Dist: pytest>=7.0.0; extra == "dev"
Requires-Dist: pytest-asyncio>=0.21.0; extra == "dev"
Requires-Dist: pytest-cov>=4.0.0; extra == "dev"
Requires-Dist: black>=23.0.0; extra == "dev"
Requires-Dist: mypy>=1.0.0; extra == "dev"
Requires-Dist: ruff>=0.1.0; extra == "dev"
Dynamic: license-file
